haystack/__init__.py
haystack/aws_client.py
haystack/cli.py
haystack/config.py
haystack/stack_finder.py
aws_haystack-0.1.0.dist-info/METADATA
aws_haystack-0.1.0.dist-info/WHEEL
aws_haystack-0.1.0.dist-info/entry_points.txt
aws_haystack-0.1.0.dist-info/licenses/LICENSE
aws_haystack-0.1.0.dist-info/RECORD
