Metadata-Version: 2.4
Name: aws-haystack
Version: 0.1.0
Summary: Find CloudFormation stacks across AWS accounts using SSO
Project-URL: Homepage, https://github.com/niklas-palm/haystack
Project-URL: Documentation, https://github.com/niklas-palm/haystack#readme
Project-URL: Repository, https://github.com/niklas-palm/haystack.git
Project-URL: Issues, https://github.com/niklas-palm/haystack/issues
Project-URL: Changelog, https://github.com/niklas-palm/haystack/blob/main/CHANGELOG.md
Author-email: Niklas Palm <niklas@enpalm.se>
License: MIT
License-File: LICENSE
Keywords: aws,cli,cloudformation,devops,sso
Classifier: Development Status :: 4 - Beta
Classifier: Environment :: Console
Classifier: Intended Audience :: Developers
Classifier: Intended Audience :: System Administrators
Classifier: License :: OSI Approved :: MIT License
Classifier: Operating System :: OS Independent
Classifier: Programming Language :: Python :: 3
Classifier: Programming Language :: Python :: 3.8
Classifier: Programming Language :: Python :: 3.9
Classifier: Programming Language :: Python :: 3.10
Classifier: Programming Language :: Python :: 3.11
Classifier: Programming Language :: Python :: 3.12
Classifier: Topic :: System :: Systems Administration
Classifier: Topic :: Utilities
Requires-Python: >=3.8
Requires-Dist: boto3>=1.34.0
Requires-Dist: click>=8.1.7
Requires-Dist: rich>=13.7.0
Provides-Extra: dev
Requires-Dist: black>=23.0.0; extra == 'dev'
Requires-Dist: isort>=5.12.0; extra == 'dev'
Requires-Dist: mypy>=1.5.0; extra == 'dev'
Requires-Dist: pytest>=7.4.0; extra == 'dev'
